whisper_pyannote_fusion/__init__.py
whisper_pyannote_fusion/audacity_labels.py
whisper_pyannote_fusion/de_wer.py
whisper_pyannote_fusion/der.py
whisper_pyannote_fusion/fusion_methods.py
whisper_pyannote_fusion/interval_utils.py
whisper_pyannote_fusion/wer.py
whisper_pyannote_fusion/whisper_pyannote_fusion.py
whisper_pyannote_fusion-0.0.5.dist-info/METADATA
whisper_pyannote_fusion-0.0.5.dist-info/WHEEL
whisper_pyannote_fusion-0.0.5.dist-info/top_level.txt
whisper_pyannote_fusion-0.0.5.dist-info/RECORD
