Metadata-Version: 2.1
Name: whisper-pyannote-fusion
Version: 0.0.5
Summary: Fuse whisper and pyannote results
Author: Mochan Shrestha
Requires-Dist: jiwer
Requires-Dist: pytest
Requires-Dist: pyannote.audio
Requires-Dist: pyannote.metrics
Requires-Dist: whisper-normalizer
Requires-Dist: intervaltree
Requires-Dist: openai-whisper
Requires-Dist: spacy
Requires-Dist: jellyfish
Requires-Dist: torch
Requires-Dist: torchvision
